simexp/__init__.py
simexp/archiver.py
simexp/collaborator_config.py
simexp/imp_clip.py
simexp/playwright_writer.py
simexp/processor.py
simexp/session_file_handler.py
simexp/session_manager.py
simexp/session_sharing.py
simexp/simex.py
simexp/simfetcher.py
simexp/timestamp_utils.py
simexp-0.4.2.dist-info/METADATA
simexp-0.4.2.dist-info/WHEEL
simexp-0.4.2.dist-info/entry_points.txt
simexp-0.4.2.dist-info/top_level.txt
simexp-0.4.2.dist-info/RECORD
