Metadata-Version: 2.4
Name: simexp
Version: 0.4.2
Summary: A web content extractor and archiver for simplenote
Home-page: https://github.com/gerico1007/simexp
Author: gerico1007
Author-email: gerico@jgwill.com
Classifier: Programming Language :: Python :: 3
Classifier: License :: OSI Approved :: MIT License
Classifier: Operating System :: OS Independent
Requires-Python: >=3.6
Requires-Dist: requests
Requires-Dist: beautifulsoup4
Requires-Dist: pyperclip
Requires-Dist: pyyaml
Requires-Dist: fetcher
Requires-Dist: playwright>=1.40.0
Requires-Dist: tlid>=0.1.0
Dynamic: author
Dynamic: author-email
Dynamic: classifier
Dynamic: description
Dynamic: description-content-type
Dynamic: home-page
Dynamic: requires-dist
Dynamic: requires-python
Dynamic: summary
